molcraft/__init__.py
molcraft/callbacks.py
molcraft/chem.py
molcraft/datasets.py
molcraft/descriptors.py
molcraft/explainers.py
molcraft/features.py
molcraft/featurizers.py
molcraft/layers.py
molcraft/losses.py
molcraft/models.py
molcraft/ops.py
molcraft/records.py
molcraft/tensors.py
molcraft/trainers.py
molcraft-0.2.3.dist-info/licenses/LICENSE
molcraft-0.2.3.dist-info/METADATA
molcraft-0.2.3.dist-info/WHEEL
molcraft-0.2.3.dist-info/top_level.txt
molcraft-0.2.3.dist-info/RECORD
