Metadata-Version: 2.4
Name: molcraft
Version: 0.2.3
Summary: Graph Neural Networks for Molecular Machine Learning
Author-email: Alexander Kensert <alexander.kensert@gmail.com>
License: MIT License
Project-URL: Homepage, https://github.com/compomics/molcraft
Keywords: python,machine-learning,deep-learning,graph-neural-networks,molecular-machine-learning,molecular-graphs,computational-chemistry,computational-biology
Classifier: Programming Language :: Python :: 3
Classifier: Intended Audience :: Science/Research
Classifier: License :: OSI Approved :: MIT License
Classifier: Operating System :: POSIX :: Linux
Requires-Python: >=3.10
License-File: LICENSE
Requires-Dist: tensorflow>=2.16
Requires-Dist: rdkit>=2023.9.5
Requires-Dist: pandas>=1.0.3
Requires-Dist: ipython>=8.12.0
Provides-Extra: gpu
Requires-Dist: tensorflow[and-cuda]>=2.16; extra == "gpu"
Dynamic: license-file
